{
  "friends": [
    {
      "timestamp": 1763374811270,
      "user": {
        "uri": "spotify:user:31ilktz5fqv575vybtkzthcniyqu",
        "name": "Rezz",
        "imageUrl": "https://i.scdn.co/image/ab6775700000ee85dde166d5c9c10ad2277bd9c5"
      },
      "track": {
        "uri": "spotify:track:2h7j0zJ2eJ1qLfyjaqQP6n",
        "name": "Coffee Breath",
        "imageUrl": "https://i.scdn.co/image/ab67616d0000b273c9fd6014bf7236a78d27a383",
        "album": {
          "uri": "spotify:album:5KOp9Y5L4icsdSUw7nwMyG",
          "name": "Coffee Breath"
        },
        "artist": {
          "uri": "spotify:artist:7H0Xu8hdP0tjpZ6z4dHquW",
          "name": "Sofia Mills"
        },
        "context": {
          "uri": "spotify:playlist:68JXTKfqFZEWO1DQRdVndh",
          "name": "playlist",
          "index": 0
        }
      }
    }
  ]
}